cleancopywriter-2025.12.12.0.dist-info/METADATA
cleancopywriter-2025.12.12.0.dist-info/WHEEL
cleancopywriter-2025.12.12.0.dist-info/entry_points.txt
cleancopywriter/__init__.py
cleancopywriter/_types.py
cleancopywriter/html/__init__.py
cleancopywriter/html/documents.py
cleancopywriter/html/generic_templates.py
cleancopywriter/html/plugin_types.py
cleancopywriter/html/prebaked/__init__.py
cleancopywriter/html/prebaked/plugins.py
cleancopywriter/html/templatifiers/__init__.py
cleancopywriter/html/templatifiers/clc.py
cleancopywriter/html/templatifiers/docnotes.py
cleancopywriter/py.typed
cleancopywriter-2025.12.12.0.dist-info/RECORD
