Metadata-Version: 2.1
Name: cleancopywriter
Version: 2025.12.12.0
Summary: Document generation tools for the cleancopy lightweight markup language
Requires-Python: >=3.12
Requires-Dist: docnote>=2025.8.5.0
Requires-Dist: docnote-extract>=2025.9.15.0
Requires-Dist: pycleancopy>=2025.8.29.0
Requires-Dist: templatey>=2025.10.13.1
